aio_actors/__init__.py
aio_actors/models.py
aio_actors/py.typed
aio_actors-0.1.4.dist-info/METADATA
aio_actors-0.1.4.dist-info/WHEEL
aio_actors-0.1.4.dist-info/RECORD
