Metadata-Version: 2.4
Name: aio-actors
Version: 0.1.4
Summary: Simple library for building actors in asyncio.
Author-email: joyanedel <iamjoyanedel@gmail.com>
Requires-Python: >=3.10
